pilab_alcohol/__init__.py
pilab_alcohol/analyse.py
pilab_alcohol/core.py
pilab_alcohol/main.py
pilab_alcohol/preprocessing.py
pilab_alcohol/registration.py
pilab_alcohol/script.py
pilab_alcohol/utils.py
pilab_alcohol-0.1.2.dist-info/METADATA
pilab_alcohol-0.1.2.dist-info/WHEEL
pilab_alcohol-0.1.2.dist-info/top_level.txt
pilab_alcohol-0.1.2.dist-info/RECORD
