Metadata-Version: 2.1
Name: pilab-alcohol
Version: 0.1.2
Summary: Analysis pipeline
Author-email: Manon Dausort <manon.dausort@uclouvain.be>
Requires-Dist: xlsxwriter
Requires-Dist: pandas
Requires-Dist: matplotlib
Requires-Dist: scikit-learn
Requires-Dist: seaborn
Requires-Dist: dipy
Requires-Dist: scikit-image
Requires-Dist: scipy
